pymimir.so
pymimir.pyi
pymdzcf-0.1.0.dist-info/WHEEL
pymdzcf-0.1.0.dist-info/LICENSE
pymdzcf-0.1.0.dist-info/top_level.txt
pymdzcf-0.1.0.dist-info/RECORD
pymdzcf-0.1.0.dist-info/METADATA
